ssseg/_C.pyd
ssseg/__init__.py
ssseg/inference.py
ssseg/test.py
ssseg/train.py
ssseg/modules/__init__.py
ssseg/modules/datasets/__init__.py
ssseg/modules/datasets/ade20k.py
ssseg/modules/datasets/atr.py
ssseg/modules/datasets/base.py
ssseg/modules/datasets/builder.py
ssseg/modules/datasets/chasedb1.py
ssseg/modules/datasets/cihp.py
ssseg/modules/datasets/cityscapes.py
ssseg/modules/datasets/coco.py
ssseg/modules/datasets/darkzurich.py
ssseg/modules/datasets/drive.py
ssseg/modules/datasets/hrf.py
ssseg/modules/datasets/lip.py
ssseg/modules/datasets/mhp.py
ssseg/modules/datasets/nighttimedriving.py
ssseg/modules/datasets/sbushadow.py
ssseg/modules/datasets/stare.py
ssseg/modules/datasets/supervisely.py
ssseg/modules/datasets/voc.py
ssseg/modules/datasets/vspw.py
ssseg/modules/datasets/pipelines/__init__.py
ssseg/modules/datasets/pipelines/evaluation.py
ssseg/modules/datasets/pipelines/transforms.py
ssseg/modules/models/__init__.py
ssseg/modules/models/backbones/__init__.py
ssseg/modules/models/backbones/beit.py
ssseg/modules/models/backbones/bisenetv1.py
ssseg/modules/models/backbones/bisenetv2.py
ssseg/modules/models/backbones/builder.py
ssseg/modules/models/backbones/cgnet.py
ssseg/modules/models/backbones/convnext.py
ssseg/modules/models/backbones/convnextv2.py
ssseg/modules/models/backbones/edgesamrepvit.py
ssseg/modules/models/backbones/erfnet.py
ssseg/modules/models/backbones/fastscnn.py
ssseg/modules/models/backbones/hiera.py
ssseg/modules/models/backbones/hrnet.py
ssseg/modules/models/backbones/mae.py
ssseg/modules/models/backbones/mit.py
ssseg/modules/models/backbones/mobilenet.py
ssseg/modules/models/backbones/mobilesamtinyvit.py
ssseg/modules/models/backbones/mobilevit.py
ssseg/modules/models/backbones/resnest.py
ssseg/modules/models/backbones/resnet.py
ssseg/modules/models/backbones/samvit.py
ssseg/modules/models/backbones/swin.py
ssseg/modules/models/backbones/timmwrapper.py
ssseg/modules/models/backbones/twins.py
ssseg/modules/models/backbones/unet.py
SSSegmentation-1.5.6.dist-info/LICENSE
SSSegmentation-1.5.6.dist-info/METADATA
SSSegmentation-1.5.6.dist-info/WHEEL
SSSegmentation-1.5.6.dist-info/top_level.txt
SSSegmentation-1.5.6.dist-info/RECORD
