Metadata-Version: 2.1
Name: SSSegmentation
Version: 1.5.6
Summary: SSSegmentation: An Open Source Supervised Semantic Segmentation Toolbox Based on PyTorch
Home-page: https://github.com/SegmentationBLWX/sssegmentation
Author: Zhenchao Jin
Author-email: charlesblwx@gmail.com
License: Apache License 2.0
Keywords: semantic segmentation
Classifier: License :: OSI Approved :: Apache Software License
Classifier: Programming Language :: Python :: 3
Classifier: Intended Audience :: Developers
Classifier: Operating System :: OS Independent
Classifier: Topic :: Utilities
Requires-Python: >=3.7
License-File: LICENSE
Requires-Dist: cython
Requires-Dist: fvcore
Requires-Dist: black
Requires-Dist: usort
Requires-Dist: ufmt
Requires-Dist: cityscapesscripts
Requires-Dist: pycocotools
Requires-Dist: pillow
Requires-Dist: pandas
Requires-Dist: opencv-python
Requires-Dist: dill
Requires-Dist: iopath
Requires-Dist: matplotlib
Requires-Dist: tqdm
Requires-Dist: argparse
Requires-Dist: numpy
Requires-Dist: scipy
Requires-Dist: chainercv
